{
	"configurations" : 
	[
		{
			"directories" : 
			[
				{
					"build" : ".",
					"childIndexes" : 
					[
						1,
						11
					],
					"hasInstallRule" : true,
					"jsonFile" : "directory-.-Debug-d0094a50bb2071803777.json",
					"minimumCMakeVersion" : 
					{
						"string" : "3.15"
					},
					"projectIndex" : 0,
					"source" : "."
				},
				{
					"build" : "dependencies",
					"childIndexes" : 
					[
						2,
						9
					],
					"hasInstallRule" : true,
					"jsonFile" : "directory-dependencies-Debug-213773dd22be3796fa39.json",
					"minimumCMakeVersion" : 
					{
						"string" : "3.15"
					},
					"parentIndex" : 0,
					"projectIndex" : 0,
					"source" : "dependencies"
				},
				{
					"build" : "dependencies/sfml",
					"childIndexes" : 
					[
						3
					],
					"hasInstallRule" : true,
					"jsonFile" : "directory-dependencies.sfml-Debug-5b392af3452b5428a1b8.json",
					"minimumCMakeVersion" : 
					{
						"string" : "3.15"
					},
					"parentIndex" : 1,
					"projectIndex" : 0,
					"source" : "dependencies/sfml"
				},
				{
					"build" : "_deps/sfml-build",
					"childIndexes" : 
					[
						4
					],
					"hasInstallRule" : true,
					"jsonFile" : "directory-_deps.sfml-build-Debug-443eb8e6264811ba9a3f.json",
					"minimumCMakeVersion" : 
					{
						"string" : "3.0.2"
					},
					"parentIndex" : 2,
					"projectIndex" : 1,
					"source" : "cmake-build-debug/_deps/sfml-src"
				},
				{
					"build" : "_deps/sfml-build/src/SFML",
					"childIndexes" : 
					[
						5,
						6,
						7,
						8
					],
					"hasInstallRule" : true,
					"jsonFile" : "directory-_deps.sfml-build.src.SFML-Debug-59858f26345abeca2d61.json",
					"minimumCMakeVersion" : 
					{
						"string" : "3.0.2"
					},
					"parentIndex" : 3,
					"projectIndex" : 1,
					"source" : "cmake-build-debug/_deps/sfml-src/src/SFML"
				},
				{
					"build" : "_deps/sfml-build/src/SFML/System",
					"hasInstallRule" : true,
					"jsonFile" : "directory-_deps.sfml-build.src.SFML.System-Debug-dbd3280bbc341b6603c0.json",
					"minimumCMakeVersion" : 
					{
						"string" : "3.0.2"
					},
					"parentIndex" : 4,
					"projectIndex" : 1,
					"source" : "cmake-build-debug/_deps/sfml-src/src/SFML/System",
					"targetIndexes" : 
					[
						4
					]
				},
				{
					"build" : "_deps/sfml-build/src/SFML/Main",
					"hasInstallRule" : true,
					"jsonFile" : "directory-_deps.sfml-build.src.SFML.Main-Debug-4ed15bbf806ba24fc74d.json",
					"minimumCMakeVersion" : 
					{
						"string" : "3.0.2"
					},
					"parentIndex" : 4,
					"projectIndex" : 1,
					"source" : "cmake-build-debug/_deps/sfml-src/src/SFML/Main",
					"targetIndexes" : 
					[
						3
					]
				},
				{
					"build" : "_deps/sfml-build/src/SFML/Window",
					"hasInstallRule" : true,
					"jsonFile" : "directory-_deps.sfml-build.src.SFML.Window-Debug-ab1d5ccfd59956b2aaa4.json",
					"minimumCMakeVersion" : 
					{
						"string" : "3.0.2"
					},
					"parentIndex" : 4,
					"projectIndex" : 1,
					"source" : "cmake-build-debug/_deps/sfml-src/src/SFML/Window",
					"targetIndexes" : 
					[
						5
					]
				},
				{
					"build" : "_deps/sfml-build/src/SFML/Graphics",
					"hasInstallRule" : true,
					"jsonFile" : "directory-_deps.sfml-build.src.SFML.Graphics-Debug-5c4951a50e8ace15d10a.json",
					"minimumCMakeVersion" : 
					{
						"string" : "3.0.2"
					},
					"parentIndex" : 4,
					"projectIndex" : 1,
					"source" : "cmake-build-debug/_deps/sfml-src/src/SFML/Graphics",
					"targetIndexes" : 
					[
						2
					]
				},
				{
					"build" : "dependencies/imgui-sfml",
					"childIndexes" : 
					[
						10
					],
					"hasInstallRule" : true,
					"jsonFile" : "directory-dependencies.imgui-sfml-Debug-d2bc53672eb7f32640c1.json",
					"minimumCMakeVersion" : 
					{
						"string" : "3.15"
					},
					"parentIndex" : 1,
					"projectIndex" : 0,
					"source" : "dependencies/imgui-sfml"
				},
				{
					"build" : "_deps/imgui-sfml-build",
					"hasInstallRule" : true,
					"jsonFile" : "directory-_deps.imgui-sfml-build-Debug-cf5909afb1e462a97daf.json",
					"minimumCMakeVersion" : 
					{
						"string" : "3.1"
					},
					"parentIndex" : 9,
					"projectIndex" : 2,
					"source" : "cmake-build-debug/_deps/imgui-sfml-src",
					"targetIndexes" : 
					[
						0
					]
				},
				{
					"build" : "src",
					"jsonFile" : "directory-src-Debug-c94b7c2814d5a21df52c.json",
					"minimumCMakeVersion" : 
					{
						"string" : "3.15"
					},
					"parentIndex" : 0,
					"projectIndex" : 0,
					"source" : "src",
					"targetIndexes" : 
					[
						1
					]
				}
			],
			"name" : "Debug",
			"projects" : 
			[
				{
					"childIndexes" : 
					[
						1,
						2
					],
					"directoryIndexes" : 
					[
						0,
						1,
						2,
						9,
						11
					],
					"name" : "AeroSim",
					"targetIndexes" : 
					[
						1
					]
				},
				{
					"directoryIndexes" : 
					[
						3,
						4,
						5,
						6,
						7,
						8
					],
					"name" : "SFML",
					"parentIndex" : 0,
					"targetIndexes" : 
					[
						2,
						3,
						4,
						5
					]
				},
				{
					"directoryIndexes" : 
					[
						10
					],
					"name" : "imgui_sfml",
					"parentIndex" : 0,
					"targetIndexes" : 
					[
						0
					]
				}
			],
			"targets" : 
			[
				{
					"directoryIndex" : 10,
					"id" : "ImGui-SFML::@0d4f94df99120bc7405e",
					"jsonFile" : "target-ImGui-SFML-Debug-ef120c8a7e163b97cb6b.json",
					"name" : "ImGui-SFML",
					"projectIndex" : 2
				},
				{
					"directoryIndex" : 11,
					"id" : "aero_sim_exe::@145eef247bfb46b6828c",
					"jsonFile" : "target-aero_sim_exe-Debug-17fe6bf420b1c1855f48.json",
					"name" : "aero_sim_exe",
					"projectIndex" : 0
				},
				{
					"directoryIndex" : 8,
					"id" : "sfml-graphics::@98af38147d5fa7e70f61",
					"jsonFile" : "target-sfml-graphics-Debug-d15729bdf3dfc3265530.json",
					"name" : "sfml-graphics",
					"projectIndex" : 1
				},
				{
					"directoryIndex" : 6,
					"id" : "sfml-main::@81ec5539f1398dd625f6",
					"jsonFile" : "target-sfml-main-Debug-6e3387ce5aa6b884b871.json",
					"name" : "sfml-main",
					"projectIndex" : 1
				},
				{
					"directoryIndex" : 5,
					"id" : "sfml-system::@8cb1db2982443611e568",
					"jsonFile" : "target-sfml-system-Debug-0a7e8fa462c50441821a.json",
					"name" : "sfml-system",
					"projectIndex" : 1
				},
				{
					"directoryIndex" : 7,
					"id" : "sfml-window::@5730451e331e3690ae65",
					"jsonFile" : "target-sfml-window-Debug-f9b24548c60dad8c46bf.json",
					"name" : "sfml-window",
					"projectIndex" : 1
				}
			]
		}
	],
	"kind" : "codemodel",
	"paths" : 
	{
		"build" : "C:/Users/wbmcg/OneDrive/Desktop/CODE/AeroSim/AeroSim/cmake-build-debug",
		"source" : "C:/Users/wbmcg/OneDrive/Desktop/CODE/AeroSim/AeroSim"
	},
	"version" : 
	{
		"major" : 2,
		"minor" : 3
	}
}
